libacmchristmas/.gitignore
libacmchristmas/__init__.py
libacmchristmas/christmas_pb2.py
libacmchristmas/image.py
libacmchristmas/tree.py
libacmchristmas-0.1.5.dist-info/LICENSE
libacmchristmas-0.1.5.dist-info/METADATA
libacmchristmas-0.1.5.dist-info/WHEEL
libacmchristmas-0.1.5.dist-info/RECORD
